command/Communication.py
command/EventServer.py
command/__init__.py
models/BaseModel.py
models/DTMF.py
models/DialPlan.py
models/FactoryModel.py
models/Input.py
models/Relay.py
models/Schedule.py
models/User.py
models/__init__.py
request/HttpRequest.py
request/__init__.py
xpe_library-0.0.3.dist-info/METADATA
xpe_library-0.0.3.dist-info/WHEEL
xpe_library-0.0.3.dist-info/top_level.txt
xpe_library-0.0.3.dist-info/RECORD
