Metadata-Version: 2.1
Name: xpe-library
Version: 0.0.3
Summary: A library to communicate with XPE line
Home-page: UNKNOWN
Author: PD Solucoes
Author-email: gabriel@pdsolucoes.com.br
License: UNKNOWN
Platform: UNKNOWN
Classifier: Programming Language :: Python :: 3
Classifier: License :: OSI Approved :: MIT License
Classifier: Operating System :: OS Independent
Requires-Python: >=3.6
